formfiller.py
forms/__init__.py
forms/base.py
forms/mod1.py
forms/mod1_old.py
forms/mod2.py
forms/usyd/__init__.py
forms/usyd/create_profile.py
forms/usyd/login_form.py
forms/usyd/personal_info_address.py
forms/usyd/personal_info_address_perm.py
forms/usyd/personal_info_contact.py
forms/usyd/personal_info_course_applications.py
forms/usyd/personal_info_details.py
forms/usyd/personal_info_enrollment.py
forms/usyd/personal_info_enrollment_status.py
forms/usyd/personal_info_fee_waiver.py
forms/usyd/personal_info_residency.py
forms/usyd/qualifications_academic_qualifications.py
forms/usyd/qualifications_highest_qualification_details.py
forms/usyd/qualifications_language_proficiency.py
forms/usyd/qualifications_record_of_exclusions.py
forms/usyd/qualifications_second_school_studies.py
forms/usyd/scholarships.py
forms/utils/etl.py
forms/utils/form_utils.py
forms/utils/logger.py
formmaster-0.1.23.dist-info/LICENSE
formmaster-0.1.23.dist-info/METADATA
formmaster-0.1.23.dist-info/WHEEL
formmaster-0.1.23.dist-info/entry_points.txt
formmaster-0.1.23.dist-info/top_level.txt
formmaster-0.1.23.dist-info/RECORD
