Metadata-Version: 2.2
Name: formmaster
Version: 0.1.23
Summary: Form automation tool for Australian university application processes
Home-page: https://github.com/haroldmei/form-master
Author: FormMaster Team
Author-email: FormMaster Team <maintainer@example.com>
Project-URL: Homepage, https://github.com/haroldmei/form-master
Project-URL: Bug Tracker, https://github.com/haroldmei/form-master/issues
Classifier: Programming Language :: Python :: 3
Classifier: Programming Language :: Python :: 3.11
Classifier: License :: OSI Approved :: MIT License
Classifier: Operating System :: Microsoft :: Windows
Requires-Python: >=3.11,<3.12
License-File: LICENSE
Requires-Dist: pandas==2.2.3
Requires-Dist: pynput==1.8.0
Requires-Dist: selenium==4.10.0
Requires-Dist: python-docx==1.1.2
Requires-Dist: pytz==2023.3
Requires-Dist: python-dateutil==2.8.2
Requires-Dist: webdriver-manager==3.8.6
Dynamic: author
Dynamic: home-page
Dynamic: requires-python
